{
  "id": "028",
  "niche": "EdTech / Образование",
  "recipient_type": "HR",
  "language": "ru",
  "subject": "Корпоративное обучение, которое сотрудники реально проходят",
  "body": "Привет, [Имя]!\n\nЗнаю, как это бывает: компания оплачивает курсы, сотрудники записываются, а completion rate — 15–20%. Деньги потрачены, навыки не получены.\n\nГлавная причина — обучение не встроено в рабочий процесс, оно «сбоку».\n\n[Продукт] встраивает микро-обучение прямо в Slack или Teams — 5 минут в день, без отрыва от задач. Клиенты достигают completion rate 78% в среднем.\n\nМогу показать как это выглядит для вашей команды?",
  "why_it_works": "soft — валидация боли без атаки + root cause + решение без трений + конкретный benchmark",
  "style": "soft"
}
